mymath_module/__init__.py
mymath_module/mymath.py
mymath_module-0.2.1.dist-info/LICENSE
mymath_module-0.2.1.dist-info/METADATA
mymath_module-0.2.1.dist-info/WHEEL
mymath_module-0.2.1.dist-info/top_level.txt
mymath_module-0.2.1.dist-info/RECORD
