Metadata-Version: 2.1
Name: mymath_module
Version: 0.2.1
Summary: A custom math operations package
Home-page: https://github.com/xing24xing/MyMathModule
Author: Khushi Pandey
Author-email: khushipandey260304.email@example.com
Classifier: Programming Language :: Python :: 3
Classifier: License :: OSI Approved :: MIT License
Classifier: Operating System :: OS Independent
Requires-Python: >=3.6
License-File: LICENSE
